phidown-0.1.24.dist-info/METADATA
phidown-0.1.24.dist-info/WHEEL
phidown-0.1.24.dist-info/entry_points.txt
phidown-0.1.24.dist-info/licenses/LICENSE
phidown/__init__.py
phidown/__main__.py
phidown/ais.py
phidown/cli.py
phidown/config.json
phidown/downloader.py
phidown/interactive_tools.py
phidown/s5cmd_utils.py
phidown/search.py
phidown/viz.py
phidown-0.1.24.dist-info/RECORD
