Metadata-Version: 2.1
Name: phidown
Version: 0.1.24
Summary: A project using AWS services and dataset tools for Sentinel data
Author-Email: Roberto Del Prete <roberto.delprete@esa.int>
License: GPLv3
Requires-Python: >=3.9
Requires-Dist: pandas>=1.5.2
Requires-Dist: s5cmd
Requires-Dist: tqdm>=4.65.0
Provides-Extra: jupyter-env
Requires-Dist: ipykernel>=6.30.1; extra == "jupyter-env"
Requires-Dist: jupyterlab-widgets>=3.0.15; extra == "jupyter-env"
Requires-Dist: jupyter-leaflet>=0.20.0; extra == "jupyter-env"
Requires-Dist: ipywidgets>=8.1.6; extra == "jupyter-env"
Provides-Extra: ais
Requires-Dist: shapely>=2.0.0; extra == "ais"
Requires-Dist: pyarrow>=21.0.0; extra == "ais"
Requires-Dist: huggingface-hub>=0.35.0; extra == "ais"
Provides-Extra: viz
Requires-Dist: leafmap[maplibre]>=0.52.2; extra == "viz"
Requires-Dist: localtileserver>=0.10.6; extra == "viz"
Requires-Dist: setuptools>=80.9.0; extra == "viz"
Requires-Dist: ipyleaflet>=0.19.2; extra == "viz"
Requires-Dist: leafmap>=0.52.2; extra == "viz"
Requires-Dist: xarray>=2024.7.0; extra == "viz"
Requires-Dist: folium>=0.18.0; extra == "viz"
Requires-Dist: rasterio>=1.4.3; extra == "viz"
Requires-Dist: matplotlib>=3.9.4; extra == "viz"
Provides-Extra: dev
Requires-Dist: pytest<9.0.0,>=7.0.0; extra == "dev"
Requires-Dist: pytest-mock>=3.10.0; extra == "dev"
Requires-Dist: flake8<8.0.0,>=6.0.0; extra == "dev"
Provides-Extra: docs
Requires-Dist: sphinx<8.0.0,>=7.0.0; extra == "docs"
Requires-Dist: sphinx-rtd-theme<4.0.0,>=1.3.0; extra == "docs"
Requires-Dist: sphinx-autodoc-typehints<3.0.0,>=1.24.0; extra == "docs"
Requires-Dist: myst-parser<4.0.0,>=3.0.0; extra == "docs"
Requires-Dist: sphinx-copybutton>=0.5.0; extra == "docs"
Requires-Dist: sphinx-autoapi<4.0.0,>=2.5.0; extra == "docs"
